{
"carriers": [
            {"code": "AS",
             "name": "Alaska Airlines",
             "country": "US",
             "operating_region": "US"
            },
            {"code": "AA",
             "name": "American Airlines",
             "country": "US",
             "operating_region": ["US","US-EU","US-CN"]
            },
            {"code": "BA",
             "name": "British Airways",
             "country": "EU",
             "operating_region": ["EU","US-EU"]
            },
            {"code": "CX",
             "name": "Cathay Pacific",
             "country": "CN",
             "operating_region": ["CN","US-CN"]
            },
            {"code": "FJ",
             "name": "Fiji Airways",
             "country": "Fiji"
            },
            {"code": "AY",
             "name": "Finnair",
             "country": "EU",
             "operating_region": ["EU","US-EU"]
            },
            {"code": "IB",
             "name": "Iberia",
             "country": "EU",
             "operating_region": ["EU","US-EU"]
            },
            {"code": "JL",
             "name": "Japan Airlines",
             "country": "Japan"
            },
            {"code": "MH",
             "name": "Malaysia Airlines",
             "country": "Malaysia"
            },
            {"code": "WY",
             "name": "Oman Air",
             "country": "Oman"
            },
            {"code": "QF",
             "name": "Qantas",
             "country": "Australia"
            },
            {"code": "QR",
             "name": "Qatar Airways",
             "country": "Qatar"
            },
            {"code": "AT",
             "name": "Royal Air Maroc",
             "country": "Morocco"
            },
            {"code": "RJ",
             "name": "Royal Jordanian",
             "country": "Jordan"
            },
            {"code": "UL",
             "name": "SriLankan Airlines",
             "country": "Sri Lanka"
            },
            
            
            
            
            
            {"code": "A3",
             "name": "Aegean Airlines",
             "country": "EU",
             "operating_region": ["EU"]
            },
            {"code": "AC",
             "name": "Air Canada",
             "country": "Canada"
            },
            {"code": "CA",
             "name": "Air China",
             "country": "CN",
             "operating_region": ["CN","US-CN"]
            },
            {"code": "AI",
             "name": "Air India",
             "country": "India"
            },
            {"code": "NZ",
             "name": "Air New Zealand",
             "country": "New Zealand"
            },
            {"code": "NH",
             "name": "All Nippon Airways",
             "country": "Japan"
            },
            {"code": "OS",
             "name": "Austrian Airlines",
             "country": "EU",
             "operating_region": ["EU","US-EU"]
            },
            {"code": "AV",
             "name": "Avianca",
             "country": "Colombia"
            },
            {"code": "SN",
             "name": "Brussels Airlines",
             "country": "EU",
             "operating_region": ["EU","US-EU"]
            },
            {"code": "CM",
             "name": "Copa Airlines",
             "country": "Panama"
            },
            {"code": "OU",
             "name": "Croatia Airlines",
             "country": "EU",
             "operating_region": ["EU"]
            },
            {"code": "MS",
             "name": "Egyptair",
             "country": "Egypt"
            },
            {"code": "ET",
             "name": "Ethiopian Airlines",
             "country": "Ethiopia"
            },
            {"code": "BR",
             "name": "Eva Air",
             "country": "CN",
             "operating_region": ["CN","US-CN"]
            },
            {"code": "LO",
             "name": "LOT Polish Airlines",
             "country": "EU",
             "operating_region": ["EU","US-EU"]
            },
            {"code": "LH",
             "name": "Lufthansa",
             "country": "EU",
             "operating_region": ["EU","US-EU"]
            },
            {"code": "ZH",
             "name": "Shenzhen Airlines",
             "country": "CN",
             "operating_region": ["CN","US-CN"]
            },
            {"code": "SQ",
             "name": "Singapore Airlines",
             "country": "Singapore"
            },
            {"code": "SA",
             "name": "South African Airways",
             "country": "South Africa"
            },
            {"code": "LX",
             "name": "Swiss International Air Lines",
             "country": "EU",
             "operating_region": ["EU","US-EU"]
            },
            {"code": "TP",
             "name": "TAP Air Portugal",
             "country": "EU",
             "operating_region": ["EU","US-EU"]
            },
            {"code": "TG",
             "name": "Thai Airways International",
             "country": "Thailand"
            },
            {"code": "TK",
             "name": "Turkish Airlines",
             "country": "Turkey"
            },
            {"code": "UA",
             "name": "United Airlines",
             "country": "US",
             "operating_region": ["US","US-EU","US-CN"]
            },
            
            
            
            {"code": "AR",
             "name": "Aerolíneas Argentinas",
             "country": "Argentina"
            },
            {"code": "AM",
             "name": "Aeroméxico",
             "country": "Mexico"
            },
            {"code": "UX",
             "name": "Air Europa",
             "country": "EU",
             "operating_region": ["EU","US-EU"]
            },
            {"code": "AF",
             "name": "Air France",
             "country": "EU",
             "operating_region": ["EU","US-EU"]
            },
            {"code": "CI",
             "name": "China Airlines",
             "country": "CN",
             "operating_region": ["CN","US-CN"]
            },
            {"code": "MU",
             "name": "China Eastern Airlines",
             "country": "CN",
             "operating_region": ["CN","US-CN"]
            },
            {"code": "DL",
             "name": "Delta Air Lines",
             "country": "US",
             "operating_region": ["US","US-EU","US-CN"]
            },
            {"code": "GA",
             "name": "Garuda Indonesia",
             "country": "Indonesia"
            },
            {"code": "KQ",
             "name": "Kenya Airways",
             "country": "Kenya"
            },
            {"code": "KL",
             "name": "KLM",
             "country": "EU",
             "operating_region": ["EU","US-EU"]
            },
            {"code": "KE",
             "name": "Korean Air",
             "country": "Korea"
            },
            {"code": "ME",
             "name": "Middle East Airlines",
             "country": "Lebanon"
            },
            {"code": "SV",
             "name": "Saudia",
             "country": "Saudi Arabia"
            },
            {"code": "SK",
             "name": "Scandinavian Airlines",
             "country": "EU",
             "operating_region": ["EU","US-EU"]
            },
            {"code": "RO",
             "name": "TAROM",
             "country": "EU",
             "operating_region": ["EU"]
            },
            {"code": "VN",
             "name": "Vietnam Airlines",
             "country": "Vietnam"
            },
            {"code": "VS",
             "name": "Virgin Atlantic",
             "country": "EU",
             "operating_region": ["EU","US-EU"]
            },
            {"code": "MF",
             "name": "XiamenAir",
             "country": "CN",
             "operating_region": ["CN","US-CN"]
            },
            
            
            
            {"code": "EI",
             "name": "Aer Lingus",
             "country": "EU",
             "operating_region": ["EU","US-EU"]
            },
            {"code": "TN",
             "name": "Air Tahiti Nui",
             "country": "EU",
             "operating_region": ["EU","US-EU"]
            },
            {"code": "DE",
             "name": "Condor",
             "country": "EU",
             "operating_region": ["EU","US-EU"]
            },
            {"code": "HU",
             "name": "Hainan Airlines",
             "country": "CN",
             "operating_region": ["CN","US-CN"]
            },
            {"code": "FI",
             "name": "Icelandair",
             "country": "EU",
             "operating_region": ["EU","US-EU"]
            },
            {"code": "PR",
             "name": "Philippine Airlines",
             "country": "Philippines"
            },
            {"code": "PD",
             "name": "Porter Airlines",
             "country": "Canada"
            },
            {"code": "JX",
             "name": "Starlux Airlines",
             "country": "CN",
             "operating_region": ["CN","US-CN"]
            },
            {"code": "VC",
             "name": "Aleutian Airways",
             "country": "US",
             "operating_region": "US"
            },
            {"code": "UP",
             "name": "Bahamassair",
             "country": "Bahamas"
            },
            {"code": "9K",
             "name": "Cape Air",
             "country": "US",
             "operating_region": "US"
            },
            {"code": "LF",
             "name": "Contour Airlines",
             "country": "US",
             "operating_region": ["US"]
            },
            {"code": "M5",
             "name": "Kenmore Air",
             "country": "US",
             "operating_region": "US"
            },
            {"code": "9X",
             "name": "Southern Airways Express",
             "country": "US",
             "operating_region": "US"
            },
            {"code": "CZ",
             "name": "China Southern Airlines",
             "country": "CN",
             "operating_region": ["CN","US-CN"]
            },
            {"code": "EY",
             "name": "Etihad Airways",
             "country": "United Arab Emirates"
            },
            {"code": "G3",
             "name": "Gol Linhas Aéreas Inteligentes",
             "country": "Brazil"
            },
            {"code": "6E",
             "name": "IndiGo",
             "country": "India"
            },
            {"code": "JA",
             "name": "JetSMART",
             "country": "Chile"
            },
            {"code": "LL",
             "name": "Level",
             "country": "EU",
             "operating_region": ["EU","US-EU"]
            },
            {"code": "LA",
             "name": "LATAM Airlines",
             "country": "Chile"
            },
            {"code": "VY",
             "name": "Vueling",
             "country": "EU",
             "operating_region": "EU"
            },
            {"code": "NT",
             "name": "Binter Canarias",
             "country": "EU",
             "operating_region": "EU"
            },
            {"code": "HO",
             "name": "Juneyao Air",
             "country": "CN",
             "operating_region": ["CN"]
            },
            {"code": "4Z",
             "name": "Airlink",
             "country": "South Africa"
            },
            {"code": "PG",
             "name": "Bangkok Airways",
             "country": "Thailand"
            },
            {"code": "B6",
             "name": "JetBlue",
             "country": "US",
             "operating_region": ["US"]
            },
            {"code": "WB",
             "name": "RwandAir",
             "country": "Rwanda"
            },
            {"code": "S7",
             "name": "S7 Airlines",
             "country": "Russia"
            },
            {"code": "VA",
             "name": "Virgin Australia",
             "country": "Australia"
            },
            {"code": "UO",
             "name": "HK Express",
             "country": "CN",
             "operating_region": ["CN"]
            },
            {"code": "JQ",
             "name": "Jetstar",
             "country": "Australia"
            },
            {"code": "SB",
             "name": "Aircalin",
             "country": "EU",
             "operating_region": ["EU"]
            },
            {"code": "LY",
             "name": "El Al",
             "country": "Isreal"
            },
            {"code": "EK",
             "name": "Emirates",
             "country": "United Arab Emirates"
            },
            {"code": "WS",
             "name": "WestJet",
             "country": "Canada"
            },
            {"code": "QN",
             "name": "SmartLynx Australia",
             "country": "Australia"
            },
            {"code": "GK",
             "name": "Jetstar Japan",
             "country": "Japan"
            },
            {"code": "YN",
             "name": "Air Creebec",
             "country": "Canada"
            },
            {"code": "EN",
             "name": "Air Dolomiti",
             "country": "EU",
             "operating_region": "EU"
            },
            {"code": "3H",
             "name": "Air Inuit",
             "country": "Canada"
            },
            {"code": "MK",
             "name": "Air Mauritius",
             "country": "Mauritius"
            },
            {"code": "JU",
             "name": "Air Serbia",
             "country": "EU",
             "operating_region": ["EU","US-EU"]
            },
            {"code": "AD",
             "name": "Azul Brazilian Airlines",
             "country": "Brazil"
            },
            {"code": "QH",
             "name": "Bamboo Airways",
             "country": "Vietnam"
            },
            {"code": "MO",
             "name": "Calm Air",
             "country": "Canada"
            },
            {"code": "5T",
             "name": "Canadian North",
             "country": "Canada"
            },
            {"code": "9M",
             "name": "Central Mountain Air",
             "country": "Canada"
            },
            {"code": "4Y",
             "name": "Discover Airlines",
             "country": "EU",
             "operating_region": ["EU","US-EU"]
            },
            {"code": "WK",
             "name": "Edelweiss Air",
             "country": "EU",
             "operating_region": ["EU","US-EU"]
            },
            {"code": "EW",
             "name": "Eurowings",
             "country": "EU",
             "operating_region": ["EU","US-EU"]
            },
            {"code": "FZ",
             "name": "Flydubai",
             "country": "United Arab Emirates"
            },
            {"code": "GF",
             "name": "Gulf Air",
             "country": "Bahrain"
            },
            {"code": "OA",
             "name": "Olympic Air",
             "country": "EU",
             "operating_region": "EU"
            },
            {"code": "PB",
             "name": "PAL Airlines",
             "country": "Canada"
            },
            {"code": "XQ",
             "name": "SunExpress",
             "country": "EU",
             "operating_region": "EU"
            },
            {"code": "VE",
             "name": "Clic Air",
             "country": "Columbia"
            },
            {"code": "B7",
             "name": "Uni Air",
             "country": "CN",
             "operating_region": "CN"
            },
            {"code": "TR",
             "name": "Scoot",
             "country": "Singapore"
            },
            {"code": "S4",
             "name": "Azores Airlines",
             "country": "EU",
             "operating_region":["EU","US-EU"]
            },
            {"code": "VF",
             "name": "AJet",
             "country": "Turkey"
            },
            {"code": "AZ",
             "name": "ITA Airways",
             "country": "EU",
             "operating_region": ["EU","US-EU"]
            },
            {"code": "XE",
             "name": "JSX",
             "country": "US",
             "operating_region":["US"]
            },
            {"code": "XK",
             "name": "Air Corsica",
             "country": "EU",
             "operating_region":["EU"]
            },
            {"code": "VT",
             "name": "Air Tahiti",
             "country": "EU",
             "operating_region":["EU"]
            },
            {"code": "BT",
             "name": "airBaltic",
             "country": "EU",
             "operating_region":["EU"]
            },
            {"code": "CE",
             "name": "Chalair Aviation",
             "country": "EU",
             "operating_region":["EU"]
            },
            {"code": "HV",
             "name": "Transavia",
             "country": "EU",
             "operating_region":["EU"]
            },
            {"code": "T7",
             "name": "Twin Jet",
             "country": "EU",
             "operating_region":["EU"]
            },
            {"code": "WM",
             "name": "Winair",
             "country": "EU",
             "operating_region":["EU"]
            },
            {"code": "AE",
             "name": "Mandarin Airlines",
             "country": "CN",
             "operating_region":["CN"]
            },
            {"code": "FM",
             "name": "Shanghai Airlines",
             "country": "CN",
             "operating_region":["CN"]
            },
            {"code": "U2",
             "name": "easyJet",
             "country": "EU",
             "operating_region":["EU"]
            },
            {"code": "WN",
             "name": "Southwest Airlines",
             "country": "US",
             "operating_region":["US"]
            },
            {"code": "JV",
             "name": "Bearskin Airlines",
             "country": "Canada"
            }
            
                   
    
  ]
}
